mara_pipelines/__init__.py
mara_pipelines/cli.py
mara_pipelines/config.py
mara_pipelines/events.py
mara_pipelines/execution.py
mara_pipelines/pipelines.py
mara_pipelines/shell.py
mara_pipelines/commands/__init__.py
mara_pipelines/commands/bash.py
mara_pipelines/commands/files.py
mara_pipelines/commands/http.py
mara_pipelines/commands/python.py
mara_pipelines/commands/sql.py
mara_pipelines/incremental_processing/__init__.py
mara_pipelines/incremental_processing/file_dependencies.py
mara_pipelines/incremental_processing/incremental_copy_status.py
mara_pipelines/incremental_processing/processed_files.py
mara_pipelines/incremental_processing/reset.py
mara_pipelines/logging/__init__.py
mara_pipelines/logging/logger.py
mara_pipelines/logging/node_cost.py
mara_pipelines/logging/pipeline_events.py
mara_pipelines/logging/run_log.py
mara_pipelines/logging/system_statistics.py
mara_pipelines/notification/__init__.py
mara_pipelines/notification/notifier.py
mara_pipelines/notification/slack.py
mara_pipelines/notification/teams.py
mara_pipelines/parallel_tasks/__init__.py
mara_pipelines/parallel_tasks/files.py
mara_pipelines/parallel_tasks/python.py
mara_pipelines/parallel_tasks/sql.py
mara_pipelines/ui/__init__.py
mara_pipelines/ui/cli.py
mara_pipelines/ui/dependency_graph.py
mara_pipelines/ui/last_runs.py
mara_pipelines/ui/node_page.py
mara_pipelines/ui/run_page.py
mara_pipelines/ui/run_time_chart.py
mara_pipelines/ui/run_time_chart.sql
mara_pipelines/ui/views.py
mara_pipelines/ui/static/common.css
mara_pipelines/ui/static/kolorwheel.js
mara_pipelines/ui/static/node-page.css
mara_pipelines/ui/static/node-page.js
mara_pipelines/ui/static/run-page.css
mara_pipelines/ui/static/run-page.js
mara_pipelines/ui/static/run-time-chart.js
mara_pipelines/ui/static/system-stats-chart.js
mara_pipelines/ui/static/timeline-chart.css
mara_pipelines/ui/static/timeline-chart.js
mara_pipelines/ui/static/utils.js
mara_pipelines-3.5.0.dist-info/LICENSE
mara_pipelines-3.5.0.dist-info/METADATA
mara_pipelines-3.5.0.dist-info/WHEEL
mara_pipelines-3.5.0.dist-info/entry_points.txt
mara_pipelines-3.5.0.dist-info/top_level.txt
mara_pipelines-3.5.0.dist-info/RECORD
