Metadata-Version: 2.1
Name: mara-pipelines
Version: 3.5.0
Summary: Opinionated lightweight ELT pipeline framework
Home-page: https://github.com/mara/mara-pipelines
Author: Mara contributors
License: MIT
Requires-Python: >=3.6
License-File: LICENSE
Requires-Dist: mara-db >=4.9.1
Requires-Dist: mara-page >=1.7.0
Requires-Dist: graphviz >=0.8
Requires-Dist: python-dateutil >=2.6.1
Requires-Dist: pythondialog >=3.4.0
Requires-Dist: more-itertools >=3.1.0
Requires-Dist: psutil >=5.4.0
Requires-Dist: requests >=2.19.1
Requires-Dist: SQLAlchemy >=1.4
Provides-Extra: test
Requires-Dist: pytest ; extra == 'test'
Requires-Dist: pytest-docker ; extra == 'test'
Requires-Dist: pytest-dependency ; extra == 'test'
Requires-Dist: mara-app >=1.5.2 ; extra == 'test'
Requires-Dist: mara-db[mssql,postgres] ; extra == 'test'
